{
  "playlist": [
    {
      "name": "MY ALL",
      "artist": "浜崎あゆみ",
      "url": "audio/music/MY ALL.mp3",
      "cover": "audio/covers/my-all.jpg"
    },
    {
      "name": "半点心",
      "artist": "草蜢",
      "url": "audio/music/半点心.mp3",
      "cover": "audio/covers/ban-dian-xin.jpg"
    },
    {
      "name": "Stay With Me",
      "artist": "未知艺术家",
      "url": "audio/music/Stay With Me.mp3",
      "cover": "audio/covers/stay-with-me.jpg"
    },
    {
      "name": "打上花火",
      "artist": "未知艺术家",
      "url": "audio/music/打上花火.mp3",
      "cover": "audio/covers/da-shang-hua-huo.jpg"
    },
    {
      "name": "生生世世爱",
      "artist": "未知艺术家",
      "url": "audio/music/生生世世爱.mp3",
      "cover": "audio/covers/sheng-sheng-shi-shi-ai.jpg"
    }
  ]
}